inout_nfc/__init__.py
inout_nfc/cli.py
inout_nfc/inout_nfc.py
inout_nfc-0.2.0.dist-info/METADATA
inout_nfc-0.2.0.dist-info/WHEEL
inout_nfc-0.2.0.dist-info/entry_points.txt
inout_nfc-0.2.0.dist-info/top_level.txt
inout_nfc-0.2.0.dist-info/RECORD
